{
  "url": "https://en.wikipedia.org/wiki/Gleditsia",
  "summary": "Gleditsia is a genus of trees in the family Fabaceae, subfamily Caesalpinioideae, native to the Americas and Asia. The Latin name commemorates Johann Gottlieb Gleditsch, director of the Berlin Botanical Garden, who died in 1786.",
  "common_name": null,
  "image": "images/Gleditsia.jpg",
  "thumbnail_url": "https://upload.wikimedia.org/wikipedia/commons/thumb/8/82/Gleditsia_triacanthos01.JPEG/330px-Gleditsia_triacanthos01.JPEG",
  "_image_attempted": true
}