{
  "url": "https://en.wikipedia.org/wiki/Nandina",
  "summary": "Nandina domestica commonly known as nandina, heavenly bamboo or sacred bamboo, is a species of flowering plant in the family Berberidaceae, native to eastern Asia from the Himalayas to Japan. It is the only member of the monotypic genus Nandina. Despite its name, it is not a true bamboo.",
  "common_name": null,
  "image": "images/Nandina.jpg",
  "thumbnail_url": "https://upload.wikimedia.org/wikipedia/commons/thumb/3/37/Nandina_domestica_cv_Otafukunante1.jpg/330px-Nandina_domestica_cv_Otafukunante1.jpg",
  "_image_attempted": true
}